filewatcher/__init__.py
filewatcher-0.0.9.dist-info/LICENSE
filewatcher-0.0.9.dist-info/METADATA
filewatcher-0.0.9.dist-info/WHEEL
filewatcher-0.0.9.dist-info/top_level.txt
filewatcher-0.0.9.dist-info/RECORD
