Metadata-Version: 2.1
Name: filewatcher
Version: 0.0.9
Summary: A helper package to monitor files
Home-page: https://github.com/cyberinfy/Tools/blob/master/filewatcher/filewatcher_usage.py
Author: Krishna
Author-email: kvrks@outlook.com
License: UNKNOWN
Platform: UNKNOWN
Classifier: Programming Language :: Python :: 3
Classifier: License :: OSI Approved :: MIT License
Classifier: Operating System :: OS Independent
Requires-Python: >=3.4
